patra_toolkit/__init__.py
patra_toolkit/exceptions.py
patra_toolkit/fairlearn_bias.py
patra_toolkit/model_store.py
patra_toolkit/patra_model_card.py
patra_toolkit/shap_xai.py
patra_toolkit/schema/schema.json
patra_toolkit-0.2.0.dist-info/licenses/LICENSE
tests/__init__.py
tests/test_authenticate.py
tests/test_modelstore_github.py
tests/test_modelstore_huggingface.py
tests/test_patra_hash_id.py
tests/test_patra_inout_data.py
tests/test_patra_mc.py
tests/test_patra_unique_id.py
patra_toolkit-0.2.0.dist-info/METADATA
patra_toolkit-0.2.0.dist-info/WHEEL
patra_toolkit-0.2.0.dist-info/top_level.txt
patra_toolkit-0.2.0.dist-info/RECORD
